pibert/__init__.py
pibert/core/__init__.py
pibert/core/model.py
pibert/physics/__init__.py
pibert/physics/physics_attention.py
pibert/pretraining/__init__.py
pibert/pretraining/ecp.py
pibert/pretraining/mpp.py
pibert/spectral/__init__.py
pibert/spectral/fourier.py
pibert/spectral/wavelet.py
pibert/utils/__init__.py
pibert/utils/utils.py
pibert-0.1.1.dist-info/LICENSE
pibert-0.1.1.dist-info/METADATA
pibert-0.1.1.dist-info/WHEEL
pibert-0.1.1.dist-info/top_level.txt
pibert-0.1.1.dist-info/RECORD
